keepahpy/__init__.py
keepahpy/sdk.py
keepahpy-0.0.2.dist-info/LICENCE
keepahpy-0.0.2.dist-info/METADATA
keepahpy-0.0.2.dist-info/WHEEL
keepahpy-0.0.2.dist-info/top_level.txt
keepahpy-0.0.2.dist-info/RECORD
