Metadata-Version: 2.1
Name: keepahpy
Version: 0.0.2
Summary: Flask-SDK for Keepah
Home-page: https://git.dsnexus.org/keepah/keepah-flask-sdk
Author: Antoine Daurat
Author-email: antoine.daurat@pwc.com
License: UNKNOWN
Platform: UNKNOWN
Classifier: Programming Language :: Python :: 3
Classifier: License :: OSI Approved :: MIT License
Classifier: Operating System :: OS Independent
